h3r/__init__.py
h3r/cffi.cpython-310-x86_64-linux-gnu.so
h3r/path_like.py
h3r/h3result.py
h3r/interface.h
h3r/error.py
h3r/lib/liblip.so.0
h3r/lib/libh3r.so.0
h3r-0.1.0.dist-info/METADATA
h3r-0.1.0.dist-info/WHEEL
h3r-0.1.0.dist-info/RECORD
